modal_tf_builder/__init__.py
modal_tf_builder/builder.py
modal_tf_gpu_builder-0.2.2.dist-info/licenses/LICENSE
modal_tf_gpu_builder-0.2.2.dist-info/METADATA
modal_tf_gpu_builder-0.2.2.dist-info/WHEEL
modal_tf_gpu_builder-0.2.2.dist-info/top_level.txt
modal_tf_gpu_builder-0.2.2.dist-info/RECORD
