Metadata-Version: 2.4
Name: modal_tf_gpu_builder
Version: 0.2.2
Summary: Builds stable Python 3.11 TensorFlow GPU environments on modal.com using Micromamba.
Author: Osvald Nigola
License: MIT
Project-URL: Homepage, https://github.com/ozzuke/modal-tf-gpu-builder
Project-URL: Issues, https://github.com/ozzuke/modal-tf-gpu-builder/issues
Classifier: Programming Language :: Python :: 3
Classifier: Programming Language :: Python :: 3.11
Classifier: Operating System :: OS Independent
Classifier: Topic :: Software Development :: Build Tools
Classifier: Topic :: Scientific/Engineering :: Artificial Intelligence
Classifier: Intended Audience :: Developers
Classifier: Intended Audience :: Science/Research
Classifier: Topic :: System :: Distributed Computing
Requires-Python: ==3.11.*
License-File: LICENSE
Requires-Dist: modal
Requires-Dist: tblib
Dynamic: license-file
